embeddings_for_trees/__init__.py
embeddings_for_trees/treelstm.py
embeddings_for_trees/typed_treelstm.py
embeddings_for_trees/data/__init__.py
embeddings_for_trees/data/jsonl_data_module.py
embeddings_for_trees/data/jsonl_dataset.py
embeddings_for_trees/data/vocabulary.py
embeddings_for_trees/models/__init__.py
embeddings_for_trees/models/treelstm2seq.py
embeddings_for_trees/models/typed_treelstm2seq.py
embeddings_for_trees/models/modules/__init__.py
embeddings_for_trees/models/modules/node_embedding.py
embeddings_for_trees/models/modules/tree_lstm_encoder.py
embeddings_for_trees/utils/__init__.py
embeddings_for_trees/utils/common.py
embeddings_for_trees/utils/test.py
embeddings_for_trees/utils/train.py
embeddings_for_trees-1.1.0.dist-info/LICENSE
embeddings_for_trees-1.1.0.dist-info/METADATA
embeddings_for_trees-1.1.0.dist-info/WHEEL
embeddings_for_trees-1.1.0.dist-info/top_level.txt
embeddings_for_trees-1.1.0.dist-info/RECORD
