Metadata-Version: 2.1
Name: embeddings-for-trees
Version: 1.1.0
Summary: Set of PyTorch modules for developing and evaluating different algorithms for embedding trees.
Home-page: https://github.com/JetBrains-Research/embeddings-for-trees
Author: Egor Spirin
Author-email: spirin.egor@gmail.com
License: MIT
Download-URL: https://pypi.org/project/embeddings-for-trees/
Keywords: treelstm,tree-lstm,embeddings-for-trees,pytorch,pytorch-lightning,ml4code,ml4se
Platform: UNKNOWN
License-File: LICENSE
Requires-Dist: torch (>=1.10.0)
Requires-Dist: pytorch-lightning (~=1.5.0)
Requires-Dist: wandb (~=0.12.0)
Requires-Dist: omegaconf (~=2.1.1)
Requires-Dist: commode-utils (>=0.4.1)
Requires-Dist: dgl (~=0.6.1)
